odoo/addons/vault_share/README.rst
odoo/addons/vault_share/__init__.py
odoo/addons/vault_share/__manifest__.py
odoo/addons/vault_share/controllers/__init__.py
odoo/addons/vault_share/controllers/main.py
odoo/addons/vault_share/data/ir_cron.xml
odoo/addons/vault_share/i18n/es.po
odoo/addons/vault_share/i18n/it.po
odoo/addons/vault_share/i18n/nl.po
odoo/addons/vault_share/i18n/vault_share.pot
odoo/addons/vault_share/models/__init__.py
odoo/addons/vault_share/models/res_company.py
odoo/addons/vault_share/models/res_config_settings.py
odoo/addons/vault_share/models/vault_share.py
odoo/addons/vault_share/models/vault_share_log.py
odoo/addons/vault_share/readme/CONTRIBUTORS.md
odoo/addons/vault_share/readme/DESCRIPTION.md
odoo/addons/vault_share/readme/ROADMAP.md
odoo/addons/vault_share/security/ir.model.access.csv
odoo/addons/vault_share/security/ir_rule.xml
odoo/addons/vault_share/static/description/icon.png
odoo/addons/vault_share/static/description/index.html
odoo/addons/vault_share/static/src/backend/vault_share.scss
odoo/addons/vault_share/static/src/backend/fields/templates.xml
odoo/addons/vault_share/static/src/backend/fields/vault_field.esm.js
odoo/addons/vault_share/static/src/backend/fields/vault_pin_field.esm.js
odoo/addons/vault_share/static/src/backend/fields/vault_share_field.esm.js
odoo/addons/vault_share/static/src/backend/fields/vault_share_file.esm.js
odoo/addons/vault_share/static/src/backend/fields/vault_share_mixin.esm.js
odoo/addons/vault_share/static/src/common/utils.esm.js
odoo/addons/vault_share/static/src/frontend/share.esm.js
odoo/addons/vault_share/tests/__init__.py
odoo/addons/vault_share/tests/test_share.py
odoo/addons/vault_share/views/menuitems.xml
odoo/addons/vault_share/views/res_config_settings_views.xml
odoo/addons/vault_share/views/templates.xml
odoo/addons/vault_share/views/vault_share_views.xml
odoo_addon_vault_share-18.0.1.0.0.2.dist-info/METADATA
odoo_addon_vault_share-18.0.1.0.0.2.dist-info/WHEEL
odoo_addon_vault_share-18.0.1.0.0.2.dist-info/top_level.txt
odoo_addon_vault_share-18.0.1.0.0.2.dist-info/RECORD
